printfx/__init__.py
printfx/threedots.py
printfx/typewriter.py
print_fx-1.0.0.dist-info/METADATA
print_fx-1.0.0.dist-info/WHEEL
print_fx-1.0.0.dist-info/top_level.txt
print_fx-1.0.0.dist-info/RECORD
